gfm/__init__.py
gfm/autolink.py
gfm/automail.py
gfm/hidden_hilite.py
gfm/semi_sane_lists.py
gfm/spaced_link.py
gfm/standalone_fenced_code.py
gfm/strikethrough.py
gfm/tasklist.py
mdx_gfm/__init__.py
mdx_partial_gfm/__init__.py
py_gfm-2.0.0.dist-info/AUTHORS
py_gfm-2.0.0.dist-info/LICENSE
py_gfm-2.0.0.dist-info/METADATA
py_gfm-2.0.0.dist-info/WHEEL
py_gfm-2.0.0.dist-info/top_level.txt
py_gfm-2.0.0.dist-info/RECORD
