Metadata-Version: 2.1
Name: py-gfm
Version: 2.0.0
Summary: An implementation of Github-Flavored Markdown written as an extension to the Python Markdown library.
Home-page: https://github.com/zopieux/py-gfm
Author: Dart Team, Alexandre Macabies
Author-email: web+oss@zopieux.com
Classifier: Environment :: Web Environment
Classifier: Intended Audience :: Developers
Classifier: Operating System :: OS Independent
Classifier: Topic :: Text Processing :: Markup
Classifier: License :: OSI Approved :: BSD License
Classifier: Programming Language :: Python :: 3
Classifier: Programming Language :: Python :: 3.8
Classifier: Programming Language :: Python :: 3.9
Classifier: Programming Language :: Python :: 3.10
Classifier: Programming Language :: Python :: 3.11
Requires-Python: >=3.8
License-File: LICENSE
License-File: AUTHORS
Requires-Dist: markdown (<4,>=3.3)
